qingtest/__init__.py
qingtest/autotest.py
qingtest/config.py
qingtest/data.py
qingtest/database.py
qingtest/elements.py
qingtest/globals.py
qingtest/injson.py
qingtest/junit.py
qingtest/locator.py
qingtest/log.py
qingtest/parse.py
qingtest/report.py
qingtest/snapshot.py
qingtest/testcase.py
qingtest/testsuite.py
qingtest/utility.py
qingtest/windows.py
qingtest/keywords/__init__.py
qingtest/keywords/common.py
qingtest/keywords/files.py
qingtest/keywords/http.py
qingtest/keywords/mobile.py
qingtest/keywords/web.py
qingtest/keywords/windows.py
qingtest/lib/__init__.py
qingtest/lib/c.py
qingtest/lib/http_handle.py
qingtest/lib/u.py
qingtest/pytransform/__init__.py
qingtest/pytransform/platforms/.DS_Store
qingtest/pytransform/platforms/darwin/.DS_Store
qingtest/pytransform/platforms/darwin/x86_64/_pytransform.dylib
qingtest/pytransform/platforms/linux/.DS_Store
qingtest/pytransform/platforms/linux/x86/_pytransform.so
qingtest/pytransform/platforms/linux/x86_64/_pytransform.so
qingtest/pytransform/platforms/windows/.DS_Store
qingtest/pytransform/platforms/windows/x86/_pytransform.dll
qingtest/pytransform/platforms/windows/x86_64/_pytransform.dll
qingtest-1.0.7.dist-info/METADATA
qingtest-1.0.7.dist-info/WHEEL
qingtest-1.0.7.dist-info/top_level.txt
qingtest-1.0.7.dist-info/RECORD
