Metadata-Version: 2.1
Name: qingtest
Version: 1.0.7
Summary: A small example package
Home-page: https://www.qingflow.com
Author: zhoujiahui
Author-email: zhoujiahui@exiao.tech
License: UNKNOWN
Platform: UNKNOWN
Classifier: Programming Language :: Python :: 3
Classifier: License :: OSI Approved :: MIT License
Classifier: Operating System :: OS Independent
Requires-Dist: selenium (==3.141.0)
Requires-Dist: xlrd (==1.2.0)
Requires-Dist: XlsxWriter (==1.3.7)
Requires-Dist: requests (==2.24.0)
Requires-Dist: Appium-Python-Client (==1.0.2)
Requires-Dist: Pillow (==8.0.1)
Requires-Dist: openpyxl (==3.0.5)
Requires-Dist: arrow (==0.17.0)
Requires-Dist: requests-toolbelt (==0.9.1)
